LICENSE
MANIFEST.in
README.rst
requirements.txt
requirements_dev.txt
setup.py
cooperative/__init__.py
cooperative/_meta.py
cooperative.egg-info/PKG-INFO
cooperative.egg-info/SOURCES.txt
cooperative.egg-info/dependency_links.txt
cooperative.egg-info/requires.txt
cooperative.egg-info/top_level.txt
cooperative/tests/__init__.py
cooperative/tests/test_cooperative.py
cooperative/tests/test_version.py
docs/Makefile
docs/conf.py
docs/getting-started.rst
docs/index.rst
docs/make.bat
docs/source/cooperative.rst
docs/source/cooperative.tests.rst
docs/source/example.rst