Metadata-Version: 1.1
Name: cooperative
Version: 0.1.10
Summary: Write computationally intensive non-blocking code without callbacks
Home-page: https://github.com/johnwlockwood/cooperative
Author: John W Lockwood IV
Author-email: john@tackletronics.com
License:                                  Apache License
